coinflow/__init__.py
coinflow/coinflowClient.py
coinflow-0.0.2.dist-info/METADATA
coinflow-0.0.2.dist-info/RECORD
coinflow-0.0.2.dist-info/WHEEL
coinflow-0.0.2.dist-info/top_level.txt
